pailab/__init__.py
pailab/__main__.py
pailab/version.py
pailab/analysis/__init__.py
pailab/analysis/plot.py
pailab/analysis/plot_helper.py
pailab/analysis/tools_jupyter.py
pailab/externals/__init__.py
pailab/externals/numpy_interface.py
pailab/externals/pandas_interface.py
pailab/externals/pytorch_interface.py
pailab/externals/sklearn_interface.py
pailab/externals/tensorflow_keras_interface.py
pailab/job_runner/__init__.py
pailab/job_runner/job_runner.py
pailab/job_runner/job_runner_factory.py
pailab/ml_repo/__init__.py
pailab/ml_repo/disk_handler.py
pailab/ml_repo/git_handler.py
pailab/ml_repo/memory_handler.py
pailab/ml_repo/numpy_handler_hdf.py
pailab/ml_repo/remote_gcs.py
pailab/ml_repo/repo.py
pailab/ml_repo/repo_objects.py
pailab/ml_repo/repo_store.py
pailab/ml_repo/repo_store_factory.py
pailab/tools/__init__.py
pailab/tools/checker.py
pailab/tools/dependency_graph.py
pailab/tools/interpretation.py
pailab/tools/tests.py
pailab/tools/tools.py
pailab/tools/tree.py
pailab-0.1.1.dist-info/LICENSE
pailab-0.1.1.dist-info/METADATA
pailab-0.1.1.dist-info/WHEEL
pailab-0.1.1.dist-info/top_level.txt
pailab-0.1.1.dist-info/RECORD
