Metadata-Version: 2.1
Name: pailab
Version: 0.1.1
Summary: pailab the integrated machine learning workbench
Home-page: https://github.com/pailabteam/pailab
Author: pailabteam
Author-email: pailab@rivacon.com
License: Apache 2.0
Keywords: platform ml version-control neural-network ml-workbench ai big data
Platform: UNKNOWN
Classifier: Development Status :: 4 - Beta
Requires-Dist: numpy (>=1.13)
Requires-Dist: plotly (>=3.5.0)
Requires-Dist: h5py (>=2.7)
Requires-Dist: pandas (>=0.20)
Requires-Dist: nbformat
Requires-Dist: deepdiff
Provides-Extra: all
Requires-Dist: sklearn ; extra == 'all'
Requires-Dist: tensorflow ; extra == 'all'
Provides-Extra: sklearn
Requires-Dist: sklearn ; extra == 'sklearn'
Provides-Extra: tensorflow
Requires-Dist: tensorflow ; extra == 'tensorflow'
